stacking_manual/__init__.py
stacking_manual/stacking_manual.py
stacking_manual-0.1.11.dist-info/METADATA
stacking_manual-0.1.11.dist-info/WHEEL
stacking_manual-0.1.11.dist-info/top_level.txt
stacking_manual-0.1.11.dist-info/RECORD
