Metadata-Version: 2.1
Name: stacking-manual
Version: 0.1.11
Summary: manual stacking package for ML
Author: kevin
License: UNKNOWN
Platform: UNKNOWN
